MANIFEST.in
README.rst
setup.py
./argparse_config/__init__.py
./argparse_config/tests/__init__.py
argparse_config.egg-info/PKG-INFO
argparse_config.egg-info/SOURCES.txt
argparse_config.egg-info/dependency_links.txt
argparse_config.egg-info/entry_points.txt
argparse_config.egg-info/not-zip-safe
argparse_config.egg-info/top_level.txt