Metadata-Version: 1.1
Name: argparse-config
Version: 0.4
Summary: Default values for argparse commandline args read from a config file.
Home-page: http://bitbucket.org/tikitu/argparse_config
Author: Tikitu de Jager
Author-email: tikitu@logophile.org
License: MIT
Platform: UNKNOWN
Classifier: Development Status :: 3 - Alpha
Classifier: License :: OSI Approved :: MIT License
Classifier: Programming Language :: Python :: 2.7
Classifier: Environment :: Console
Classifier: Operating System :: OS Independent
Classifier: Topic :: Utilities
